DjangoSyncMaster/__init__.py
DjangoSyncMaster/main.py
djangosyncmaster-1.0.2.dist-info/licenses/LICENSE
djangosyncmaster-1.0.2.dist-info/METADATA
djangosyncmaster-1.0.2.dist-info/WHEEL
djangosyncmaster-1.0.2.dist-info/top_level.txt
djangosyncmaster-1.0.2.dist-info/RECORD
