Metadata-Version: 2.4
Name: DjangoSyncMaster
Version: 1.0.2
Summary: Powerful tool for truly synchronizing data and its relationships in database tables. Truly maps Foreign Keys and their on_delete rules in Django.
Author: Nyx – Shadow in the Bits
Author-email: Leonardo Cardoso Caurin <leonardo.cardoso.caurin@gmail.com>
License-Expression: GPL-3.0-or-later
Project-URL: Homepage, https://github.com/Master-osVetnik/DjangoSyncMaster
Project-URL: Issues, https://github.com/Master-osVetnik/DjangoSyncMaster/issues
Classifier: Programming Language :: Python :: 3
Classifier: Framework :: Django
Classifier: Operating System :: OS Independent
Requires-Python: >=3.9
License-File: LICENSE
Requires-Dist: django>=4.0
Dynamic: license-file
